camera_management/__init__.py
camera_management/definitions.py
camera_management/_camera_backends/.python-version
camera_management/_camera_backends/__init__.py
camera_management/_camera_backends/avt_handler.py
camera_management/_camera_backends/basler_handler.py
camera_management/_camera_backends/oak_handler.py
camera_management/camera_app/__init__.py
camera_management/camera_app/camera_interface.py
camera_management/camera_app/static/deveritec-favicon.png
camera_management/camera_app/static/bootstrap/css/bootstrap.min.css
camera_management/camera_app/static/bootstrap/js/bootstrap.bundle.min.js
camera_management/camera_app/temp/configs/8091.json
camera_management/camera_app/temp/configs/8091.json.1
camera_management/camera_app/temp/configs/8091.json.2
camera_management/camera_app/temp/configs/8091.json.3
camera_management/camera_app/temp/configs/8091.json.4
camera_management/camera_app/temp/configs/8092.json
camera_management/camera_app/temp/configs/8092.json.1
camera_management/camera_app/temp/configs/8092.json.2
camera_management/camera_app/temp/configs/8092.json.3
camera_management/camera_app/temp/configs/8092.json.4
camera_management/camera_app/temp/configs/8093.json
camera_management/camera_app/temp/configs/8093.json.1
camera_management/camera_app/temp/configs/8093.json.2
camera_management/camera_app/temp/configs/8093.json.3
camera_management/camera_app/temp/configs/8093.json.4
camera_management/camera_app/temp/configs/8094.json
camera_management/camera_app/temp/configs/8094.json.1
camera_management/camera_app/temp/configs/8094.json.2
camera_management/camera_app/temp/configs/8094.json.3
camera_management/camera_app/temp/configs/8094.json.4
camera_management/camera_app/temp/configs/8095.json
camera_management/camera_app/temp/configs/8095.json.1
camera_management/camera_app/temp/configs/8095.json.2
camera_management/camera_app/temp/configs/8095.json.3
camera_management/camera_app/temp/configs/8095.json.4
camera_management/camera_app/temp/configs/8096.json
camera_management-1.1.0.dist-info/METADATA
camera_management-1.1.0.dist-info/WHEEL
camera_management-1.1.0.dist-info/licenses/LICENSE
camera_management-1.1.0.dist-info/RECORD
