Metadata-Version: 2.1
Name: camera-management
Version: 1.1.0
Summary: Camera Management Module
Project-URL: Homepage, https://github.com/TrafoToolkit/camera-management
Author-email: Simon Michel <simon.michel@deveritec.com>, Martin Eckardt <martin.eckardt@deveritec.com>
License-File: LICENSE
Classifier: Development Status :: 5 - Production/Stable
Classifier: License :: OSI Approved :: MIT License
Classifier: Operating System :: Microsoft :: Windows
Classifier: Operating System :: POSIX :: Linux
Classifier: Programming Language :: Python :: 3
Classifier: Topic :: Scientific/Engineering :: Image Processing
Requires-Python: >=3.10
Requires-Dist: depthai
Requires-Dist: flask
Requires-Dist: numpy>=1.24.0
Requires-Dist: opencv-contrib-python>=4.7.0.68
Requires-Dist: pydantic-numpy
Requires-Dist: pydantic==2.5.3
Requires-Dist: pygrabber~=0.1; platform_system == 'win32'
Requires-Dist: pyobjc-framework-avfoundation; platform_system == 'Darwin'
Requires-Dist: pypylon
Requires-Dist: pyudev; sys_platform == 'linux'
Requires-Dist: pyusb-chain>=0.2.7; platform_system == 'win32'
Requires-Dist: pyvirtualcam~=0.10.2; platform_system == 'win32'
Requires-Dist: requests
Requires-Dist: tabulate
Requires-Dist: waitress
